<?xml version="1.0" encoding="utf-8" ?>
<XnaContent>
<Asset Type="System.Collections.Generic.Dictionary[System.String, Microsoft.Xna.Framework.Rectangle]">	
	<Item><Key>unicorn_atlas_blue_east_0.png</Key><Value>793 480 59 158</Value></Item>
	<Item><Key>unicorn_atlas_blue_east_1.png</Key><Value>138 0 67 161</Value></Item>
	<Item><Key>unicorn_atlas_blue_east_2.png</Key><Value>341 479 64 156</Value></Item>
	<Item><Key>unicorn_atlas_blue_east_3.png</Key><Value>914 0 59 158</Value></Item>
	<Item><Key>unicorn_atlas_blue_east_4.png</Key><Value>474 647 62 161</Value></Item>
	<Item><Key>unicorn_atlas_blue_east_5.png</Key><Value>730 316 61 156</Value></Item>
	<Item><Key>unicorn_atlas_blue_north_0.png</Key><Value>1094 644 58 159</Value></Item>
	<Item><Key>unicorn_atlas_blue_north_1.png</Key><Value>138 652 67 161</Value></Item>
	<Item><Key>unicorn_atlas_blue_north_2.png</Key><Value>603 0 62 156</Value></Item>
	<Item><Key>unicorn_atlas_blue_north_3.png</Key><Value>1036 0 58 159</Value></Item>
	<Item><Key>unicorn_atlas_blue_north_4.png</Key><Value>275 158 64 161</Value></Item>
	<Item><Key>unicorn_atlas_blue_north_5.png</Key><Value>207 0 66 156</Value></Item>
	<Item><Key>unicorn_atlas_blue_south_0.png</Key><Value>915 320 59 158</Value></Item>
	<Item><Key>unicorn_atlas_blue_south_1.png</Key><Value>69 0 67 161</Value></Item>
	<Item><Key>unicorn_atlas_blue_south_2.png</Key><Value>407 158 64 156</Value></Item>
	<Item><Key>unicorn_atlas_blue_south_3.png</Key><Value>915 160 59 158</Value></Item>
	<Item><Key>unicorn_atlas_blue_south_4.png</Key><Value>603 158 62 161</Value></Item>
	<Item><Key>unicorn_atlas_blue_south_5.png</Key><Value>602 637 62 156</Value></Item>
	<Item><Key>unicorn_atlas_blue_west_0.png</Key><Value>1034 802 58 159</Value></Item>
	<Item><Key>unicorn_atlas_blue_west_1.png</Key><Value>0 326 67 161</Value></Item>
	<Item><Key>unicorn_atlas_blue_west_2.png</Key><Value>667 0 62 156</Value></Item>
	<Item><Key>unicorn_atlas_blue_west_3.png</Key><Value>974 802 58 159</Value></Item>
	<Item><Key>unicorn_atlas_blue_west_4.png</Key><Value>473 321 64 161</Value></Item>
	<Item><Key>unicorn_atlas_blue_west_5.png</Key><Value>207 316 66 156</Value></Item>
	<Item><Key>unicorn_atlas_green_east_0.png</Key><Value>913 960 59 158</Value></Item>
	<Item><Key>unicorn_atlas_green_east_1.png</Key><Value>0 652 67 161</Value></Item>
	<Item><Key>unicorn_atlas_green_east_2.png</Key><Value>342 963 64 156</Value></Item>
	<Item><Key>unicorn_atlas_green_east_3.png</Key><Value>854 480 59 158</Value></Item>
	<Item><Key>unicorn_atlas_green_east_4.png</Key><Value>474 484 62 161</Value></Item>
	<Item><Key>unicorn_atlas_green_east_5.png</Key><Value>730 790 61 156</Value></Item>
	<Item><Key>unicorn_atlas_green_north_0.png</Key><Value>1034 641 58 159</Value></Item>
	<Item><Key>unicorn_atlas_green_north_1.png</Key><Value>0 978 67 161</Value></Item>
	<Item><Key>unicorn_atlas_green_north_2.png</Key><Value>538 805 62 156</Value></Item>
	<Item><Key>unicorn_atlas_green_north_3.png</Key><Value>915 480 58 159</Value></Item>
	<Item><Key>unicorn_atlas_green_north_4.png</Key><Value>408 642 64 161</Value></Item>
	<Item><Key>unicorn_atlas_green_north_5.png</Key><Value>207 158 66 156</Value></Item>
	<Item><Key>unicorn_atlas_green_south_0.png</Key><Value>793 160 59 158</Value></Item>
	<Item><Key>unicorn_atlas_green_south_1.png</Key><Value>69 326 67 161</Value></Item>
	<Item><Key>unicorn_atlas_green_south_2.png</Key><Value>409 0 64 156</Value></Item>
	<Item><Key>unicorn_atlas_green_south_3.png</Key><Value>731 0 59 158</Value></Item>
	<Item><Key>unicorn_atlas_green_south_4.png</Key><Value>666 484 62 161</Value></Item>
	<Item><Key>unicorn_atlas_green_south_5.png</Key><Value>666 963 62 156</Value></Item>
	<Item><Key>unicorn_atlas_green_west_0.png</Key><Value>974 641 58 159</Value></Item>
	<Item><Key>unicorn_atlas_green_west_1.png</Key><Value>69 815 67 161</Value></Item>
	<Item><Key>unicorn_atlas_green_west_2.png</Key><Value>667 158 62 156</Value></Item>
	<Item><Key>unicorn_atlas_green_west_3.png</Key><Value>976 0 58 159</Value></Item>
	<Item><Key>unicorn_atlas_green_west_4.png</Key><Value>407 479 64 161</Value></Item>
	<Item><Key>unicorn_atlas_green_west_5.png</Key><Value>207 632 66 156</Value></Item>
	<Item><Key>unicorn_atlas_none_east_0.png</Key><Value>730 948 59 158</Value></Item>
	<Item><Key>unicorn_atlas_none_east_1.png</Key><Value>69 163 67 161</Value></Item>
	<Item><Key>unicorn_atlas_none_east_2.png</Key><Value>408 805 64 156</Value></Item>
	<Item><Key>unicorn_atlas_none_east_3.png</Key><Value>791 948 59 158</Value></Item>
	<Item><Key>unicorn_atlas_none_east_4.png</Key><Value>666 321 62 161</Value></Item>
	<Item><Key>unicorn_atlas_none_east_5.png</Key><Value>603 321 61 156</Value></Item>
	<Item><Key>unicorn_atlas_none_north_0.png</Key><Value>976 161 58 159</Value></Item>
	<Item><Key>unicorn_atlas_none_north_1.png</Key><Value>0 489 67 161</Value></Item>
	<Item><Key>unicorn_atlas_none_north_2.png</Key><Value>602 795 62 156</Value></Item>
	<Item><Key>unicorn_atlas_none_north_3.png</Key><Value>974 963 58 159</Value></Item>
	<Item><Key>unicorn_atlas_none_north_4.png</Key><Value>407 316 64 161</Value></Item>
	<Item><Key>unicorn_atlas_none_north_5.png</Key><Value>206 978 66 156</Value></Item>
	<Item><Key>unicorn_atlas_none_south_0.png</Key><Value>913 800 59 158</Value></Item>
	<Item><Key>unicorn_atlas_none_south_1.png</Key><Value>0 0 67 161</Value></Item>
	<Item><Key>unicorn_atlas_none_south_2.png</Key><Value>343 0 64 156</Value></Item>
	<Item><Key>unicorn_atlas_none_south_3.png</Key><Value>852 800 59 158</Value></Item>
	<Item><Key>unicorn_atlas_none_south_4.png</Key><Value>538 642 62 161</Value></Item>
	<Item><Key>unicorn_atlas_none_south_5.png</Key><Value>538 484 62 156</Value></Item>
	<Item><Key>unicorn_atlas_none_west_0.png</Key><Value>975 480 58 159</Value></Item>
	<Item><Key>unicorn_atlas_none_west_1.png</Key><Value>69 978 67 161</Value></Item>
	<Item><Key>unicorn_atlas_none_west_2.png</Key><Value>602 479 62 156</Value></Item>
	<Item><Key>unicorn_atlas_none_west_3.png</Key><Value>1095 322 58 159</Value></Item>
	<Item><Key>unicorn_atlas_none_west_4.png</Key><Value>473 158 64 161</Value></Item>
	<Item><Key>unicorn_atlas_none_west_5.png</Key><Value>274 948 66 156</Value></Item>
	<Item><Key>unicorn_atlas_red_east_0.png</Key><Value>854 640 59 158</Value></Item>
	<Item><Key>unicorn_atlas_red_east_1.png</Key><Value>0 163 67 161</Value></Item>
	<Item><Key>unicorn_atlas_red_east_2.png</Key><Value>408 963 64 156</Value></Item>
	<Item><Key>unicorn_atlas_red_east_3.png</Key><Value>852 960 59 158</Value></Item>
	<Item><Key>unicorn_atlas_red_east_4.png</Key><Value>474 810 62 161</Value></Item>
	<Item><Key>unicorn_atlas_red_east_5.png</Key><Value>730 474 61 156</Value></Item>
	<Item><Key>unicorn_atlas_red_north_0.png</Key><Value>1096 161 58 159</Value></Item>
	<Item><Key>unicorn_atlas_red_north_1.png</Key><Value>69 489 67 161</Value></Item>
	<Item><Key>unicorn_atlas_red_north_2.png</Key><Value>539 0 62 156</Value></Item>
	<Item><Key>unicorn_atlas_red_north_3.png</Key><Value>1034 963 58 159</Value></Item>
	<Item><Key>unicorn_atlas_red_north_4.png</Key><Value>342 800 64 161</Value></Item>
	<Item><Key>unicorn_atlas_red_north_5.png</Key><Value>207 790 66 156</Value></Item>
	<Item><Key>unicorn_atlas_red_south_0.png</Key><Value>793 320 59 158</Value></Item>
	<Item><Key>unicorn_atlas_red_south_1.png</Key><Value>138 815 67 161</Value></Item>
	<Item><Key>unicorn_atlas_red_south_2.png</Key><Value>341 158 64 156</Value></Item>
	<Item><Key>unicorn_atlas_red_south_3.png</Key><Value>853 0 59 158</Value></Item>
	<Item><Key>unicorn_atlas_red_south_4.png</Key><Value>538 963 62 161</Value></Item>
	<Item><Key>unicorn_atlas_red_south_5.png</Key><Value>474 973 62 156</Value></Item>
	<Item><Key>unicorn_atlas_red_west_0.png</Key><Value>1035 322 58 159</Value></Item>
	<Item><Key>unicorn_atlas_red_west_1.png</Key><Value>138 163 67 161</Value></Item>
	<Item><Key>unicorn_atlas_red_west_2.png</Key><Value>475 0 62 156</Value></Item>
	<Item><Key>unicorn_atlas_red_west_3.png</Key><Value>1036 161 58 159</Value></Item>
	<Item><Key>unicorn_atlas_red_west_4.png</Key><Value>275 321 64 161</Value></Item>
	<Item><Key>unicorn_atlas_red_west_5.png</Key><Value>207 474 66 156</Value></Item>
	<Item><Key>unicorn_atlas_white_east_0.png</Key><Value>793 640 59 158</Value></Item>
	<Item><Key>unicorn_atlas_white_east_1.png</Key><Value>138 326 67 161</Value></Item>
	<Item><Key>unicorn_atlas_white_east_2.png</Key><Value>275 484 64 156</Value></Item>
	<Item><Key>unicorn_atlas_white_east_3.png</Key><Value>854 320 59 158</Value></Item>
	<Item><Key>unicorn_atlas_white_east_4.png</Key><Value>602 953 62 161</Value></Item>
	<Item><Key>unicorn_atlas_white_east_5.png</Key><Value>730 632 61 156</Value></Item>
	<Item><Key>unicorn_atlas_white_north_0.png</Key><Value>1094 483 58 159</Value></Item>
	<Item><Key>unicorn_atlas_white_north_1.png</Key><Value>138 489 67 161</Value></Item>
	<Item><Key>unicorn_atlas_white_north_2.png</Key><Value>666 805 62 156</Value></Item>
	<Item><Key>unicorn_atlas_white_north_3.png</Key><Value>1094 805 58 159</Value></Item>
	<Item><Key>unicorn_atlas_white_north_4.png</Key><Value>341 316 64 161</Value></Item>
	<Item><Key>unicorn_atlas_white_north_5.png</Key><Value>138 978 66 156</Value></Item>
	<Item><Key>unicorn_atlas_white_south_0.png</Key><Value>854 160 59 158</Value></Item>
	<Item><Key>unicorn_atlas_white_south_1.png</Key><Value>69 652 67 161</Value></Item>
	<Item><Key>unicorn_atlas_white_south_2.png</Key><Value>275 642 64 156</Value></Item>
	<Item><Key>unicorn_atlas_white_south_3.png</Key><Value>792 0 59 158</Value></Item>
	<Item><Key>unicorn_atlas_white_south_4.png</Key><Value>539 316 62 161</Value></Item>
	<Item><Key>unicorn_atlas_white_south_5.png</Key><Value>666 647 62 156</Value></Item>
	<Item><Key>unicorn_atlas_white_west_0.png</Key><Value>1094 966 58 159</Value></Item>
	<Item><Key>unicorn_atlas_white_west_1.png</Key><Value>0 815 67 161</Value></Item>
	<Item><Key>unicorn_atlas_white_west_2.png</Key><Value>539 158 62 156</Value></Item>
	<Item><Key>unicorn_atlas_white_west_3.png</Key><Value>1096 0 58 159</Value></Item>
	<Item><Key>unicorn_atlas_white_west_4.png</Key><Value>341 637 64 161</Value></Item>
	<Item><Key>unicorn_atlas_white_west_5.png</Key><Value>275 0 66 156</Value></Item>

</Asset>
</XnaContent>